game/__init__.py
game/cli.py
game/main.py
game/assets/fonts/font_placeholder
game/assets/images/pygame_lofi.png
game/assets/images/backgrounds/bg1/bg_full.png
game/assets/images/backgrounds/bg1/bg_grass.png
game/assets/images/backgrounds/bg1/bg_sky.png
game/assets/images/pc/spyke/idle/1.png
game/assets/images/pc/spyke/idle/2.png
game/assets/images/pc/spyke/jump/1.png
game/assets/images/pc/spyke/jump/2.png
game/assets/images/pc/spyke/jump/3.png
game/assets/images/pc/spyke/walk/1.png
game/assets/images/pc/spyke/walk/2.png
game/assets/images/pc/spyke/walk/3.png
game/assets/images/pc/spyke/walk/4.png
game/assets/images/pc/spyke/walk/5.png
game/assets/images/pc/spyke/walk/6.png
game/assets/images/pc/spyke/walk/7.png
game/assets/images/platforms/grass_platforms/floor.png
game/assets/images/platforms/grass_platforms/large1.png
game/assets/images/platforms/grass_platforms/large2.png
game/assets/images/platforms/grass_platforms/large3.png
game/assets/images/platforms/grass_platforms/medium1.png
game/assets/images/platforms/grass_platforms/medium2.png
game/assets/images/platforms/grass_platforms/small1.png
game/assets/images/platforms/grass_platforms/small2.png
game/assets/music/demo.mp3
game/assets/sounds/demo.wav
game/compositions/__init__.py
game/compositions/loader.py
game/configs/__init__.py
game/configs/input_tester_joystick.json
game/configs/settings.toml
game/configs/compositions/__init__.py
game/configs/compositions/editor_export.eei.json
game/configs/controllers/__init__.py
game/configs/controllers/generic.toml
game/core/__init__.py
game/core/app.py
game/core/audio.py
game/core/clock.py
game/core/config.py
game/core/resources.py
game/editor/__init__.py
game/editor/model.py
game/editor/registry.py
game/entities/__init__.py
game/entities/base.py
game/entities/collider.py
game/entities/mass.py
game/entities/platforms.py
game/entities/playable.py
game/entities/sprite_collider.py
game/entities/spyke_player.py
game/entities/visible_mass.py
game/entities/void.py
pygame_videogame_maker-1.0.10.dist-info/licenses/LICENSE
pygame_videogame_maker-1.0.10.dist-info/METADATA
pygame_videogame_maker-1.0.10.dist-info/WHEEL
pygame_videogame_maker-1.0.10.dist-info/entry_points.txt
pygame_videogame_maker-1.0.10.dist-info/top_level.txt
pygame_videogame_maker-1.0.10.dist-info/RECORD
