Metadata-Version: 2.4
Name: pygame-videogame-maker
Version: 1.0.10
Summary: A simple videogame maker using Pygame.
Author-email: Daiego <daiego@email.com>
License: Copyright 2025 Diego Delgado Chaves
Project-URL: Homepage, https://github.com/daiego/PygameVideogameMaker
Project-URL: Issues, https://github.com/daiego/PygameVideogameMaker/issues
Keywords: pygame,game,editor
Classifier: Programming Language :: Python :: 3
Classifier: License :: OSI Approved :: MIT License
Classifier: Operating System :: OS Independent
Requires-Python: >=3.12
License-File: LICENSE
Requires-Dist: pillow>=12.0.0
Requires-Dist: pygame>=2.6.1
Requires-Dist: rich>=14.2.0
Dynamic: license-file
